hxntools/CompositeBroker.py
hxntools/__init__.py
hxntools/_version.py
hxntools/anc350.py
hxntools/device.py
hxntools/elem_fluo_lines.py
hxntools/interp.py
hxntools/motor_info.py
hxntools/scan_info.py
hxntools/scan_monitor.py
hxntools/scan_number.py
hxntools/scan_status.py
hxntools/scans.py
hxntools/shutter.py
hxntools/struck_scaler.py
hxntools/detectors/__init__.py
hxntools/detectors/beamstatus.py
hxntools/detectors/dexela.py
hxntools/detectors/hxn_xspress3.py
hxntools/detectors/mercury.py
hxntools/detectors/merlin.py
hxntools/detectors/timepix.py
hxntools/detectors/trigger_mixins.py
hxntools/detectors/utils.py
hxntools/detectors/zebra.py
hxntools/handlers/__init__.py
hxntools/handlers/bulkdata.py
hxntools/handlers/hxn_handler.py
hxntools/handlers/rasmi2.py
hxntools/handlers/timepix.py
hxntools/handlers/xspress3.py
hxntools-0.6.5.dist-info/licenses/LICENSE
hxntools-0.6.5.dist-info/METADATA
hxntools-0.6.5.dist-info/WHEEL
hxntools-0.6.5.dist-info/top_level.txt
hxntools-0.6.5.dist-info/RECORD
