Metadata-Version: 2.4
Name: hxntools
Version: 0.6.5
Summary: NSLS-II Hard X-ray Nanoprobe data acquisition tools
Author-email: Brookhaven National Laboratory <DAMA@bnl.gov>
License-Expression: BSD-3-Clause
Project-URL: Homepage, https://github.com/NSLS-II-HXN/hxntools
Project-URL: Bug Tracker, https://github.com/NSLS-II-HXN/hxntools/issues
Project-URL: Discussions, https://github.com/NSLS-II-HXN/hxntools/discussions
Project-URL: Changelog, https://github.com/NSLS-II-HXN/hxntools/releases
Classifier: Development Status :: 5 - Production/Stable
Classifier: Intended Audience :: Science/Research
Classifier: Intended Audience :: Developers
Classifier: Natural Language :: English
Classifier: Operating System :: OS Independent
Classifier: Programming Language :: Python
Classifier: Programming Language :: Python :: 3
Classifier: Programming Language :: Python :: 3 :: Only
Classifier: Programming Language :: Python :: 3.10
Classifier: Programming Language :: Python :: 3.11
Classifier: Programming Language :: Python :: 3.12
Classifier: Topic :: Scientific/Engineering
Requires-Python: >=3.10
License-File: LICENSE
Requires-Dist: bluesky
Requires-Dist: boltons
Requires-Dist: cycler
Requires-Dist: databroker
Requires-Dist: h5py
Requires-Dist: matplotlib
Requires-Dist: nslsii
Requires-Dist: numpy
Requires-Dist: ophyd
Requires-Dist: pandas
Requires-Dist: pyepics
Requires-Dist: scipy
Dynamic: license-file
